<odoo>
  <data>
    <!-- explicit list view definition -->
<!--
    <record model="ir.ui.view" id="padetha_reports.list">
      <field name="name">padetha_reports list</field>
      <field name="model">padetha_reports.padetha_reports</field>
      <field name="arch" type="xml">
        <list>
          <field name="name"/>
          <field name="value"/>
          <field name="value2"/>
        </list>
      </field>
    </record>
-->

    <!-- actions opening views on models -->
<!--
    <record model="ir.actions.act_window" id="padetha_reports.action_window">
      <field name="name">padetha_reports window</field>
      <field name="res_model">padetha_reports.padetha_reports</field>
      <field name="view_mode">list,form</field>
    </record>
-->

    <!-- server action to the one above -->
<!--
    <record model="ir.actions.server" id="padetha_reports.action_server">
      <field name="name">padetha_reports server</field>
      <field name="model_id" ref="model_padetha_reports_padetha_reports"/>
      <field name="state">code</field>
      <field name="code">
        action = {
          "type": "ir.actions.act_window",
          "view_mode": "list,form",
          "res_model": model._name,
        }
      </field>
    </record>
-->

    <!-- Top menu item -->
<!--
    <menuitem name="padetha_reports" id="padetha_reports.menu_root"/>
-->
    <!-- menu categories -->
<!--
    <menuitem name="Menu 1" id="padetha_reports.menu_1" parent="padetha_reports.menu_root"/>
    <menuitem name="Menu 2" id="padetha_reports.menu_2" parent="padetha_reports.menu_root"/>
-->
    <!-- actions -->
<!--
    <menuitem name="List" id="padetha_reports.menu_1_list" parent="padetha_reports.menu_1"
              action="padetha_reports.action_window"/>
    <menuitem name="Server to list" id="padetha_reports" parent="padetha_reports.menu_2"
              action="padetha_reports.action_server"/>
-->
  </data>
</odoo>
